khnlp/__init__.py
khnlp/logger.py
khnlp/crf/__init__.py
khnlp/crf/_pipeline.py
khnlp/pos/__init__.py
khnlp/pos/_pipline.py
khnlp/pos/tagger.py
khnlp/pos/util.py
khnlp/romanize/__init__.py
khnlp/romanize/_pipline.py
khnlp/romanize/romanizer.py
khnlp/romanize/util.py
khnlp/segment/__init__.py
khnlp/segment/_pipline.py
khnlp/segment/tokenizer.py
khnlp/segment/util.py
khnlp/util/__init__.py
khnlp/util/data.py
khnlp/util/file.py
khnlp/util/shell.py
khnlp-0.0.3.dist-info/METADATA
khnlp-0.0.3.dist-info/WHEEL
khnlp-0.0.3.dist-info/top_level.txt
khnlp-0.0.3.dist-info/RECORD
