Metadata-Version: 2.1
Name: khnlp
Version: 0.0.3
Summary: Khmer NLP Toolkits
Home-page: https://github.com/IDRI-LAB/Khmer-NLP-Tools/
Author: LEANG Sotheara
Author-email: leangsotheara@gmail.com
License: UNKNOWN
Keywords: ,,
Platform: UNKNOWN
Classifier: Development Status :: 3 - Alpha
Classifier: Intended Audience :: Developers
Classifier: License :: OSI Approved :: MIT License
Requires-Python: >=3.6
Requires-Dist: tqdm (==4.61.0)
Requires-Dist: sklearn-crfsuite (==0.3.6)
Requires-Dist: scikit-learn (==0.23.2)
Requires-Dist: pydub (==0.25.1)
